PGram/__init__.py
pgram-0.0.9.dist-info/METADATA
pgram-0.0.9.dist-info/WHEEL
pgram-0.0.9.dist-info/top_level.txt
pgram-0.0.9.dist-info/RECORD
