Metadata-Version: 2.4
Name: PGram
Version: 0.0.9
Summary: Blazingly fast start async telegram bot on top of the aiogram with postgres channels
Author-email: XyncNet <code@xync.net>
License: MIT
Project-URL: Homepage, https://github.com/XyncNet/PGram
Project-URL: Repository, https://github.com/XyncNet/PGram
Keywords: aiogram,xync-net,postgres,channels,signals
Requires-Python: >=3.12
Requires-Dist: aiogram
Requires-Dist: asyncpg
Provides-Extra: dev
Requires-Dist: build; extra == "dev"
Requires-Dist: python-dotenv; extra == "dev"
Requires-Dist: pre-commit; extra == "dev"
Requires-Dist: setuptools-scm[toml]; extra == "dev"
Requires-Dist: twine; extra == "dev"
